setup.cfg
setup.py
poline/__init__.py
poline/_com_collections.py
poline/core.py
poline/fields.py
poline/utilfuncs.py
poline.egg-info/PKG-INFO
poline.egg-info/SOURCES.txt
poline.egg-info/dependency_links.txt
poline.egg-info/entry_points.txt
poline.egg-info/top_level.txt