Metadata-Version: 1.1
Name: poline
Version: 0.6
Summary: Python one-liners: Awk-like one-liners for python
Home-page: https://github.com/riolet/pol
Author: Rohana Rezel
Author-email: poline@riolet.com
License: UNKNOWN
Platform: UNKNOWN
Classifier: Topic :: System :: Operating System
Classifier: Development Status :: 5 - Production/Stable
Classifier: Environment :: Console
Classifier: License :: OSI Approved :: MIT License
Classifier: Programming Language :: Python :: 2
Classifier: Programming Language :: Python :: 2.7
Classifier: Programming Language :: Python :: 3
Classifier: Programming Language :: Python :: 3.2
Classifier: Programming Language :: Python :: 3.3
Classifier: Programming Language :: Python :: 3.4
Classifier: Programming Language :: Python :: 3.5
Classifier: Programming Language :: Python :: 3.6
